CHANGELOG.rst
LICENSE
MANIFEST.in
README.rst
check_puppetdb_node.py
setup.py
check_puppetdb_node.egg-info/PKG-INFO
check_puppetdb_node.egg-info/SOURCES.txt
check_puppetdb_node.egg-info/dependency_links.txt
check_puppetdb_node.egg-info/entry_points.txt
check_puppetdb_node.egg-info/requires.txt
check_puppetdb_node.egg-info/top_level.txt