Metadata-Version: 1.1
Name: check-puppetdb-node
Version: 0.0.1
Summary: Nagios plugin to check Puppet run status through PuppetDB
Home-page: https://github.com/daenney/check_puppetdb_node
Author: Daniele Sluijters
Author-email: daniele.sluijters+pypi@gmail.com
License: Apache License 2.0
Keywords: puppet puppetdb nagios agent run status
Platform: UNKNOWN
Classifier: Development Status :: 4 - Beta
Classifier: Intended Audience :: System Administrators
Classifier: Natural Language :: English
Classifier: License :: OSI Approved :: Apache Software License
Classifier: Operating System :: POSIX
Classifier: Programming Language :: Python :: 2
Classifier: Programming Language :: Python :: 2.6
Classifier: Programming Language :: Python :: 2.7
Classifier: Programming Language :: Python :: 3
Classifier: Programming Language :: Python :: 3.3
Classifier: Programming Language :: Python :: 3.4
Classifier: Topic :: System :: Monitoring
